{
	"vms": [
		{
			"vmname": "vm0",
			"username": "beans",
			"password": "beans",
			"hostname": "beans.dev",
			"ostype": "Ubuntu_64",
			"memory": "2048",
			"cpu": "1",
			"ssh": {
				"install-ssh-server": "true",
				"authorized": ["ssh-ed25519 AAAAC3NzaC1lZDI1NTE5AAAAIPKvNb5pcQ/ZouwdIv3PmNtsuOCFTMLTsta6F9qfjHDI phonybeans@dev.com"],
				"allow-pw": "true"
			},
			"nics": [
				{
					"type": "nat",
					"dhcp": "true"
				},
				{
					"type": "hostonly",
					"adapter": "vboxnet0",
					"dhcp": "false",
					"address": ["192.168.56.40/24"],
					"dns": ["8.8.8.8", "1.1.1.1"]
				}
			],
			"storage": [
				{
					"type": "hdd",
					"device": "0",
					"port": "0",
					"medium": "PATH",
					"size": "20000"
				},
				{
					"type": "dvddrive",
					"device": "0",
					"port": "1",
					"medium": "PATH"
				},
				{
					"type": "dvddrive",
					"device": "0",
					"port": "2",
					"medium": "SEED"
				}
			]
		} 	
	]
}
